{
  "label": "true",
  "thread": "580332109782466561",
  "cascade": [
    {
      "user_id": "564457556",
      "text": "#4u9525 from fl380 to fl110 in 8 min? that's average rate of descent 3375 fpm! than levelled off at fl068? what the hell was going on there?",
      "time": "2015-03-24 11:35:31",
      "support": "supporting",
      "tweet_id": "580332109782466561",
      "retweet_count": 32
    },
    {
      "user_id": "76173847",
      "time": "2015-03-24 11:36:26",
      "text": "@AirSmolik Only entered FL380 for a few mins prior too. So sad.",
      "tweet_id": "580332339055726592",
      "retweet_count": 1,
      "support": "comment"
    },
    {
      "user_id": "487077385",
      "time": "2015-03-24 11:36:45",
      "text": "@AirSmolik but at a controlled speed (unless readings were out), which makes it even more bizarre. I hope they find the real answers soon",
      "tweet_id": "580332419871539200",
      "retweet_count": 1,
      "support": "comment"
    },
    {
      "user_id": "69660431",
      "time": "2015-03-24 11:37:01",
      "text": "@AirSmolik descent rate is not that unusual.",
      "tweet_id": "580332487819165696",
      "retweet_count": 1,
      "support": "comment"
    },
    {
      "user_id": "6575472",
      "time": "2015-03-24 11:37:34",
      "text": "@AirSmolik Im thinking structurql failure - qnd then depressure etc cockpit window etc ? Trqgique",
      "tweet_id": "580332626541694976",
      "retweet_count": 1,
      "support": "supporting"
    },
    {
      "user_id": "506250177",
      "time": "2015-03-24 11:37:47",
      "text": "@AirSmolik And apperently no turn to avoid terrain. Straight ahead into the mountains.",
      "tweet_id": "580332678274240512",
      "retweet_count": 1,
      "support": "supporting"
    },
    {
      "user_id": "167101680",
      "time": "2015-03-24 11:42:05",
      "text": "@AirSmolik pilots may have been suffering a Hypoxie",
      "tweet_id": "580333762677997569",
      "retweet_count": 1,
      "support": "comment"
    },
    {
      "user_id": "104491970",
      "time": "2015-03-24 11:48:33",
      "text": "@AirSmolik @abundare78 would point to a cabin depressurisation",
      "tweet_id": "580335390197981184",
      "retweet_count": 1,
      "support": "comment"
    },
    {
      "user_id": "205846189",
      "time": "2015-03-24 12:04:26",
      "text": "@AirSmolik my thoughts exactly. rate is not unusual but surely crew were aware of where they were &amp; terrain... this'll be interesting.",
      "tweet_id": "580339386262380544",
      "retweet_count": 1,
      "support": "supporting"
    },
    {
      "user_id": "18867170",
      "time": "2015-03-24 13:18:11",
      "text": "@AirSmolik EMERG DESC, set FL68, started descent and lost consciousness before able to set higher ALT? Seems likely...",
      "tweet_id": "580357944815972353",
      "retweet_count": 1,
      "support": "comment"
    }
  ]
}