{"contributors": null, "truncated": false, "text": "@bxzwei @Tristan8002 Das habe ich mich auch gefragt. Warum haben die Piloten die Maschine in die Alpen gelenkt? (1/2)", "in_reply_to_status_id": 580394670536130561, "id": 580397779576578048, "favorite_count": 0, "source": "<a href=\"http://twitter.com\" rel=\"nofollow\">Twitter Web Client</a>", "retweeted": false, "coordinates": null, "entities": {"symbols": [], "user_mentions": [{"id": 1190982396, "indices": [0, 7], "id_str": "1190982396", "screen_name": "bxzwei", "name": "Bj\u00f6rn B."}, {"id": 61951451, "indices": [8, 20], "id_str": "61951451", "screen_name": "Tristan8002", "name": "Tristan8002"}], "hashtags": [], "urls": []}, "in_reply_to_screen_name": "bxzwei", "id_str": "580397779576578048", "retweet_count": 0, "in_reply_to_user_id": 1190982396, "favorited": false, "user": {"follow_request_sent": false, "profile_use_background_image": true, "profile_text_color": "333333", "default_profile_image": true, "id": 2188976540, "profile_background_image_url_https": "https://abs.twimg.com/images/themes/theme1/bg.png", "verified": false, "profile_location": null, "profile_image_url_https": "https://abs.twimg.com/sticky/default_profile_images/default_profile_2_normal.png", "profile_sidebar_fill_color": "DDEEF6", "entities": {"description": {"urls": []}}, "followers_count": 0, "profile_sidebar_border_color": "C0DEED", "id_str": "2188976540", "profile_background_color": "C0DEED", "listed_count": 0, "is_translation_enabled": false, "utc_offset": null, "statuses_count": 3, "description": "", "friends_count": 31, "location": "", "profile_link_color": "0084B4", "profile_image_url": "http://abs.twimg.com/sticky/default_profile_images/default_profile_2_normal.png", "following": false, "geo_enabled": false, "profile_background_image_url": "http://abs.twimg.com/images/themes/theme1/bg.png", "name": "Patrick Lenzen", "lang": "de", "profile_background_tile": false, "favourites_count": 1, "screen_name": "PatrickLenzen", "notifications": false, "url": null, "created_at": "Mon Nov 11 20:45:51 +0000 2013", "contributors_enabled": false, "time_zone": null, "protected": false, "default_profile": true, "is_translator": false}, "geo": null, "in_reply_to_user_id_str": "1190982396", "lang": "de", "created_at": "Tue Mar 24 15:56:28 +0000 2015", "in_reply_to_status_id_str": "580394670536130561", "place": null}
