{"contributors": null, "truncated": false, "text": "@BILD mag kotzen", "in_reply_to_status_id": 576358041215508480, "id": 576373103800020992, "favorite_count": 0, "source": "<a href=\"http://twitter.com/download/android\" rel=\"nofollow\">Twitter for Android</a>", "retweeted": false, "coordinates": null, "entities": {"symbols": [], "user_mentions": [{"id": 9204502, "indices": [0, 5], "id_str": "9204502", "screen_name": "BILD", "name": "BILD"}], "hashtags": [], "urls": []}, "in_reply_to_screen_name": "BILD", "id_str": "576373103800020992", "retweet_count": 0, "in_reply_to_user_id": 9204502, "favorited": false, "user": {"follow_request_sent": false, "profile_use_background_image": false, "profile_text_color": "000000", "default_profile_image": false, "id": 2275067477, "profile_background_image_url_https": "https://abs.twimg.com/images/themes/theme1/bg.png", "verified": false, "profile_location": null, "profile_image_url_https": "https://pbs.twimg.com/profile_images/590922987215392769/llRxQK9P_normal.jpg", "profile_sidebar_fill_color": "000000", "entities": {"description": {"urls": []}}, "followers_count": 157, "profile_sidebar_border_color": "000000", "id_str": "2275067477", "profile_background_color": "000000", "listed_count": 5, "is_translation_enabled": false, "utc_offset": null, "statuses_count": 4075, "description": "Essen, Bier und Schlafen ergibt mein Leben. Tate is perfect af. \u00d7 anti social \u00d7 AHS \u00d7 obsessed with bands and too many other things", "friends_count": 217, "location": "", "profile_link_color": "9266CC", "profile_image_url": "http://pbs.twimg.com/profile_images/590922987215392769/llRxQK9P_normal.jpg", "following": false, "geo_enabled": true, "profile_banner_url": "https://pbs.twimg.com/profile_banners/2275067477/1429721467", "profile_background_image_url": "http://abs.twimg.com/images/themes/theme1/bg.png", "name": "liz langdon\u264c", "lang": "de", "profile_background_tile": false, "favourites_count": 4545, "screen_name": "tpttrecks", "notifications": false, "url": null, "created_at": "Sat Jan 11 16:01:27 +0000 2014", "contributors_enabled": false, "time_zone": null, "protected": false, "default_profile": false, "is_translator": false}, "geo": null, "in_reply_to_user_id_str": "9204502", "lang": "de", "created_at": "Fri Mar 13 13:23:51 +0000 2015", "in_reply_to_status_id_str": "576358041215508480", "place": null}
