{
  "label": "unverified",
  "thread": "524925730053181440",
  "cascade": [
    {
      "user_id": "19038934",
      "text": "shooter still on loose after uniformed soldier shot at #ottawa's war memorial, across road from parliament. mp's being taken out of offices.",
      "time": "2014-10-22 14:10:21",
      "support": "supporting",
      "tweet_id": "524925730053181440",
      "retweet_count": 837
    },
    {
      "user_id": "238486480",
      "time": "2014-10-22 14:11:51",
      "text": "@CBCAlerts  this is just horrible :(",
      "tweet_id": "524926108257775617",
      "retweet_count": 0,
      "support": "comment"
    },
    {
      "user_id": "2525132137",
      "time": "2014-10-22 14:11:56",
      "text": "@CBCAlerts I hope they are being taken out of their offices and thrown out on to the street.",
      "tweet_id": "524926131032850432",
      "retweet_count": 0,
      "support": "comment"
    },
    {
      "user_id": "22251439",
      "time": "2014-10-22 14:12:36",
      "text": "RT @CBCAlerts: Shooter still on loose after uniformed soldier shot at #Ottawa's War Memorial, across road from Parliament.",
      "tweet_id": "524926297567293440",
      "retweet_count": 0,
      "support": "comment"
    },
    {
      "user_id": "77076143",
      "time": "2014-10-22 14:13:48",
      "text": "\u201c@CBCAlerts: Shooter still on loose after uniformed soldier shot at War Memorial, across road from Parliament.  :( sad...",
      "tweet_id": "524926598576099328",
      "retweet_count": 0,
      "support": "supporting"
    },
    {
      "user_id": "839910636",
      "time": "2014-10-22 14:14:23",
      "text": "@CBCAlerts @CBCNews , well blame Steven Harper , he's all for guns , wants this country to become like the US of A",
      "tweet_id": "524926744714047488",
      "retweet_count": 0,
      "support": "comment"
    },
    {
      "user_id": "201563247",
      "time": "2014-10-22 14:14:24",
      "text": "@CBCAlerts @amberstefani",
      "tweet_id": "524926749638131712",
      "retweet_count": 0,
      "support": "comment"
    },
    {
      "user_id": "339911220",
      "time": "2014-10-22 14:19:24",
      "text": "@CBCAlerts reporting soldier shot in Ottawa. Very sad news.",
      "tweet_id": "524928009493827585",
      "retweet_count": 0,
      "support": "supporting"
    },
    {
      "user_id": "243243291",
      "time": "2014-10-22 14:21:07",
      "text": "@CBCAlerts Chris. Not about guns. about Canada and Isis.Muslim extremist ran over two soldiers in Quebec. Blame Harper for allowing cars",
      "tweet_id": "524928439678427136",
      "retweet_count": 0,
      "support": "comment"
    },
    {
      "user_id": "18524109",
      "time": "2014-10-22 14:30:09",
      "text": "@ChristoferU @CBCAlerts @CBCNews Seriously? Likelihood that it's an ISIS attack and THIS is your response???",
      "tweet_id": "524930715021213696",
      "retweet_count": 0,
      "support": "comment"
    },
    {
      "user_id": "294115652",
      "time": "2014-10-22 14:31:12",
      "text": "@ChristoferU @CBCAlerts @CBCNews You're an idiot.",
      "tweet_id": "524930977211355136",
      "retweet_count": 0,
      "support": "denying"
    },
    {
      "user_id": "2483222413",
      "time": "2014-10-22 14:38:04",
      "text": "@CBCAlerts OMG.",
      "tweet_id": "524932703682969601",
      "retweet_count": 0,
      "support": "comment"
    },
    {
      "user_id": "839910636",
      "time": "2014-10-22 18:40:30",
      "text": "@tsklierenko  , I guess your a fan of the fascist Stevie and his band of crap , so that tells me what you are !",
      "tweet_id": "524993716336197632",
      "retweet_count": 0,
      "support": "comment"
    },
    {
      "user_id": "839910636",
      "time": "2014-10-22 19:24:25",
      "text": "@lifebythecreek , you pick a fight with people you better expect something in return , we use to be peacekeepers ,so be careful what you get",
      "tweet_id": "525004768415322112",
      "retweet_count": 0,
      "support": "comment"
    },
    {
      "user_id": "18524109",
      "time": "2014-10-22 19:58:54",
      "text": "@ChristoferU Have u read this paper from Muslm Brthrhood? From 1991. We did NOT \"pick a fight\". They brought it HERE. http://t.co/lnffeP6qHf",
      "tweet_id": "525013445184602112",
      "retweet_count": 0,
      "support": "comment"
    },
    {
      "user_id": "363935285",
      "time": "2014-10-22 22:03:54",
      "text": "@tsklierenko @ChristoferU things aren't as black and white as you may think. Picking a fight on Twitter isn't cool, bro.",
      "tweet_id": "525044903865511937",
      "retweet_count": 0,
      "support": "comment"
    },
    {
      "user_id": "839910636",
      "time": "2014-10-22 22:10:15",
      "text": "@cristinaresteve @tsklierenko , everyone is entitled to a opinion , no fight here , you don't know me , I don't know you",
      "tweet_id": "525046502474137600",
      "retweet_count": 0,
      "support": "comment"
    },
    {
      "user_id": "839910636",
      "time": "2014-10-22 22:15:18",
      "text": "@cristinaresteve @tsklierenko , sorry about the soldier who died , terrible , no disrespect meant , don't believe gov't course is correct",
      "tweet_id": "525047771221737472",
      "retweet_count": 0,
      "support": "comment"
    },
    {
      "user_id": "363935285",
      "time": "2014-10-22 22:21:29",
      "text": "@ChristoferU I definitely hear that and agree \ud83d\udc4d",
      "tweet_id": "525049327459504128",
      "retweet_count": 0,
      "support": "supporting"
    }
  ]
}